pulsar_spout/__init__.py
pulsar_spout/pulsar_spout.py
pulsar_spout-0.0.23.dist-info/DESCRIPTION.rst
pulsar_spout-0.0.23.dist-info/METADATA
pulsar_spout-0.0.23.dist-info/RECORD
pulsar_spout-0.0.23.dist-info/WHEEL
pulsar_spout-0.0.23.dist-info/metadata.json
pulsar_spout-0.0.23.dist-info/top_level.txt
