Metadata-Version: 2.0
Name: pulsar-spout
Version: 0.0.23
Summary: Python spout for Heron
Home-page: https://github.com/twitter/heron
Author: Heron Team
Author-email: heronstreaming@gmail.com
License: UNKNOWN
Keywords: heron topology python pulsar spout
Platform: UNKNOWN
Classifier: Development Status :: 3 - Alpha
Classifier: Intended Audience :: Developers
Classifier: Programming Language :: Python :: 2.7
Requires-Dist: heronpy (>=0.0.1)
Requires-Dist: protobuf (>=2.5.0,<3)
Requires-Dist: pulsar-client (==1.19.dev2)
